qlient/core/__init__.py
qlient/core/__meta__.py
qlient/core/_internal.py
qlient/core/_types.py
qlient/core/backends.py
qlient/core/builder.py
qlient/core/clients.py
qlient/core/exceptions.py
qlient/core/models.py
qlient/core/plugins.py
qlient/core/proxies.py
qlient/core/schema/__init__.py
qlient/core/schema/models.py
qlient/core/schema/parser.py
qlient/core/schema/providers.py
qlient/core/schema/schema.py
qlient/core/settings.py
qlient_core-1.0.1.dist-info/LICENSE
qlient_core-1.0.1.dist-info/WHEEL
qlient_core-1.0.1.dist-info/METADATA
qlient_core-1.0.1.dist-info/RECORD
